quickDash/__init__.py
quickDash/data_representation.py
quickDash/static/homeIcon.svg
quickDash/static/onClick.js
quickDash/static/style.css
quickDash/templates/master.html
quickdash-0.2.dist-info/METADATA
quickdash-0.2.dist-info/WHEEL
quickdash-0.2.dist-info/licenses/LICENSE
quickdash-0.2.dist-info/RECORD
