Metadata-Version: 2.4
Name: quickDash
Version: 0.2
Summary: A package that uses flask to create quick and user friendly dashboards to show both information and data
Author: Ronnie Peters
License-File: LICENSE
Classifier: Operating System :: OS Independent
Classifier: Programming Language :: Python :: 3
Requires-Python: >=3.9
Requires-Dist: flask
